{
    "datetime": "2025-12-02T22:00:00-05:00",
    "Imports (MW)": 1246.0,
    "Exports (MW)": 1737.0,
    "Net Import/Exports (MW)": 491.0,
    "Power Generated (MW)": 18248.0,
    "Ontario Demand (MW)": 17757.0,
    "Total Emissions (tonnes)": 1961.0,
    "CO2e Intensity (g/kWh)": 107.0,
    "nuclear (%)": 43.0,
    "hydro (%)": 19.4,
    "gas (%)": 30.5,
    "wind (%)": 6.9,
    "biofuel (%)": 0.2,
    "solar (%)": 0.0,
    "nuclear (MW)": 7848.0,
    "hydro (MW)": 3534.0,
    "gas (MW)": 5561.0,
    "wind (MW)": 1268.0,
    "biofuel (MW)": 29.0,
    "solar (MW)": 0.0
}