{
    "datetime": "2025-05-08T16:00:00-04:00",
    "Imports (MW)": 634.0,
    "Exports (MW)": 3259.0,
    "Net Import/Exports (MW)": 2625.0,
    "Power Generated (MW)": 16900.0,
    "Ontario Demand (MW)": 14275.0,
    "Total Emissions (tonnes)": 606.0,
    "CO2e Intensity (g/kWh)": 36.0,
    "nuclear (%)": 56.6,
    "hydro (%)": 24.6,
    "gas (%)": 7.7,
    "wind (%)": 9.4,
    "biofuel (%)": 0.0,
    "solar (%)": 1.7,
    "nuclear (MW)": 9563.0,
    "hydro (MW)": 4164.0,
    "gas (MW)": 1302.0,
    "wind (MW)": 1587.0,
    "biofuel (MW)": 0.0,
    "solar (MW)": 283.0
}