{
    "datetime": "2026-02-03T05:00:00-05:00",
    "Imports (MW)": 612.0,
    "Exports (MW)": 3267.0,
    "Net Import/Exports (MW)": 2655.0,
    "Power Generated (MW)": 19926.0,
    "Ontario Demand (MW)": 17271.0,
    "Total Emissions (tonnes)": 2458.0,
    "CO2e Intensity (g/kWh)": 123.0,
    "nuclear (%)": 41.6,
    "hydro (%)": 17.9,
    "gas (%)": 33.4,
    "wind (%)": 6.5,
    "biofuel (%)": 0.1,
    "solar (%)": 0.0,
    "nuclear (MW)": 8288.0,
    "hydro (MW)": 3566.0,
    "gas (MW)": 6652.0,
    "wind (MW)": 1290.0,
    "biofuel (MW)": 15.0,
    "solar (MW)": 0.0
}