{
    "datetime": "2024-08-02T19:00:00-04:00",
    "Imports (MW)": 2667.0,
    "Exports (MW)": 2401.0,
    "Net Import/Exports (MW)": -266.0,
    "Power Generated (MW)": 21528.0,
    "Ontario Demand (MW)": 21794.0,
    "Total Emissions (tonnes)": 2337.0,
    "CO2e Intensity (g/kWh)": 109.0,
    "nuclear (%)": 46.7,
    "hydro (%)": 23.0,
    "gas (%)": 29.0,
    "wind (%)": 0.4,
    "biofuel (%)": 0.5,
    "solar (%)": 0.4,
    "nuclear (MW)": 10052.0,
    "hydro (MW)": 4957.0,
    "gas (MW)": 6242.0,
    "wind (MW)": 83.0,
    "biofuel (MW)": 109.0,
    "solar (MW)": 85.0
}