{
    "datetime": "2023-05-29T03:00:00-04:00",
    "Imports (MW)": 9.0,
    "Exports (MW)": 1952.0,
    "Net Import/Exports (MW)": 1943.0,
    "Power Generated (MW)": 13833.0,
    "Ontario Demand (MW)": 11890.0,
    "Total Emissions (tonnes)": 81.0,
    "CO2e Intensity (g/kWh)": 6.0,
    "nuclear (%)": 60.9,
    "hydro (%)": 30.4,
    "gas (%)": 0.9,
    "wind (%)": 7.7,
    "biofuel (%)": 0.1,
    "solar (%)": 0.0,
    "nuclear (MW)": 8428.0,
    "hydro (MW)": 4203.0,
    "gas (MW)": 129.0,
    "wind (MW)": 1062.0,
    "biofuel (MW)": 11.0,
    "solar (MW)": 0.0
}