{
    "datetime": "2025-12-18T11:00:00-05:00",
    "Imports (MW)": 109.0,
    "Exports (MW)": 2813.0,
    "Net Import/Exports (MW)": 2704.0,
    "Power Generated (MW)": 20626.0,
    "Ontario Demand (MW)": 17922.0,
    "Total Emissions (tonnes)": 1615.0,
    "CO2e Intensity (g/kWh)": 78.0,
    "nuclear (%)": 40.0,
    "hydro (%)": 17.0,
    "gas (%)": 22.5,
    "wind (%)": 19.5,
    "biofuel (%)": 0.1,
    "solar (%)": 0.9,
    "nuclear (MW)": 8249.0,
    "hydro (MW)": 3506.0,
    "gas (MW)": 4633.0,
    "wind (MW)": 4014.0,
    "biofuel (MW)": 29.0,
    "solar (MW)": 195.0
}