{
    "datetime": "2025-06-15T09:00:00-04:00",
    "Imports (MW)": 9.0,
    "Exports (MW)": 2312.0,
    "Net Import/Exports (MW)": 2303.0,
    "Power Generated (MW)": 15116.0,
    "Ontario Demand (MW)": 12813.0,
    "Total Emissions (tonnes)": 444.0,
    "CO2e Intensity (g/kWh)": 29.0,
    "nuclear (%)": 60.8,
    "hydro (%)": 30.2,
    "gas (%)": 6.8,
    "wind (%)": 1.1,
    "biofuel (%)": 0.1,
    "solar (%)": 1.0,
    "nuclear (MW)": 9184.0,
    "hydro (MW)": 4569.0,
    "gas (MW)": 1031.0,
    "wind (MW)": 172.0,
    "biofuel (MW)": 10.0,
    "solar (MW)": 149.0
}