{
    "datetime": "2024-04-30T21:00:00-04:00",
    "Imports (MW)": 505.0,
    "Exports (MW)": 1140.0,
    "Net Import/Exports (MW)": 635.0,
    "Power Generated (MW)": 16553.0,
    "Ontario Demand (MW)": 15918.0,
    "Total Emissions (tonnes)": 1667.0,
    "CO2e Intensity (g/kWh)": 101.0,
    "nuclear (%)": 33.6,
    "hydro (%)": 33.9,
    "gas (%)": 28.1,
    "wind (%)": 4.4,
    "biofuel (%)": 0.0,
    "solar (%)": 0.0,
    "nuclear (MW)": 5556.0,
    "hydro (MW)": 5606.0,
    "gas (MW)": 4656.0,
    "wind (MW)": 735.0,
    "biofuel (MW)": 0.0,
    "solar (MW)": 0.0
}