{
    "datetime": "2024-03-13T21:00:00-04:00",
    "Imports (MW)": 152.0,
    "Exports (MW)": 1582.0,
    "Net Import/Exports (MW)": 1430.0,
    "Power Generated (MW)": 17328.0,
    "Ontario Demand (MW)": 15898.0,
    "Total Emissions (tonnes)": 1040.0,
    "CO2e Intensity (g/kWh)": 60.0,
    "nuclear (%)": 48.2,
    "hydro (%)": 30.1,
    "gas (%)": 15.9,
    "wind (%)": 5.3,
    "biofuel (%)": 0.5,
    "solar (%)": 0.0,
    "nuclear (MW)": 8350.0,
    "hydro (MW)": 5214.0,
    "gas (MW)": 2753.0,
    "wind (MW)": 927.0,
    "biofuel (MW)": 84.0,
    "solar (MW)": 0.0
}