{
    "datetime": "2026-06-14T18:00:00-04:00",
    "Imports (MW)": 149.0,
    "Exports (MW)": 3180.0,
    "Net Import/Exports (MW)": 3031.0,
    "Power Generated (MW)": 19836.0,
    "Ontario Demand (MW)": 16805.0,
    "Total Emissions (tonnes)": 1278.0,
    "CO2e Intensity (g/kWh)": 64.0,
    "nuclear (%)": 47.9,
    "hydro (%)": 24.7,
    "gas (%)": 19.0,
    "wind (%)": 7.5,
    "biofuel (%)": 0.1,
    "solar (%)": 0.3,
    "nuclear (MW)": 9507.0,
    "hydro (MW)": 4898.0,
    "gas (MW)": 3773.0,
    "wind (MW)": 1482.0,
    "biofuel (MW)": 16.0,
    "solar (MW)": 65.0
}