{
    "datetime": "2025-08-04T14:00:00-04:00",
    "Imports (MW)": 184.0,
    "Exports (MW)": 1734.0,
    "Net Import/Exports (MW)": 1550.0,
    "Power Generated (MW)": 20086.0,
    "Ontario Demand (MW)": 18536.0,
    "Total Emissions (tonnes)": 2058.0,
    "CO2e Intensity (g/kWh)": 102.0,
    "nuclear (%)": 43.0,
    "hydro (%)": 25.4,
    "gas (%)": 28.3,
    "wind (%)": 1.3,
    "biofuel (%)": 0.1,
    "solar (%)": 1.6,
    "nuclear (MW)": 8643.0,
    "hydro (MW)": 5111.0,
    "gas (MW)": 5693.0,
    "wind (MW)": 265.0,
    "biofuel (MW)": 29.0,
    "solar (MW)": 313.0
}