{
    "datetime": "2024-08-21T14:00:00-04:00",
    "Imports (MW)": 9.0,
    "Exports (MW)": 1836.0,
    "Net Import/Exports (MW)": 1827.0,
    "Power Generated (MW)": 17597.0,
    "Ontario Demand (MW)": 15770.0,
    "Total Emissions (tonnes)": 837.0,
    "CO2e Intensity (g/kWh)": 48.0,
    "nuclear (%)": 58.9,
    "hydro (%)": 20.7,
    "gas (%)": 12.3,
    "wind (%)": 6.5,
    "biofuel (%)": 0.2,
    "solar (%)": 1.4,
    "nuclear (MW)": 10370.0,
    "hydro (MW)": 3651.0,
    "gas (MW)": 2159.0,
    "wind (MW)": 1146.0,
    "biofuel (MW)": 31.0,
    "solar (MW)": 240.0
}