{
    "datetime": "2025-12-28T19:00:00-05:00",
    "Imports (MW)": 264.0,
    "Exports (MW)": 3189.0,
    "Net Import/Exports (MW)": 2925.0,
    "Power Generated (MW)": 21093.0,
    "Ontario Demand (MW)": 18168.0,
    "Total Emissions (tonnes)": 1758.0,
    "CO2e Intensity (g/kWh)": 83.0,
    "nuclear (%)": 45.6,
    "hydro (%)": 18.7,
    "gas (%)": 24.6,
    "wind (%)": 10.5,
    "biofuel (%)": 0.1,
    "solar (%)": 0.0,
    "nuclear (MW)": 9612.0,
    "hydro (MW)": 3951.0,
    "gas (MW)": 5185.0,
    "wind (MW)": 2214.0,
    "biofuel (MW)": 13.0,
    "solar (MW)": 0.0
}