{
    "datetime": "2024-06-19T03:00:00-04:00",
    "Imports (MW)": 212.0,
    "Exports (MW)": 1577.0,
    "Net Import/Exports (MW)": 1365.0,
    "Power Generated (MW)": 17291.0,
    "Ontario Demand (MW)": 15926.0,
    "Total Emissions (tonnes)": 1067.0,
    "CO2e Intensity (g/kWh)": 62.0,
    "nuclear (%)": 57.6,
    "hydro (%)": 16.8,
    "gas (%)": 15.7,
    "wind (%)": 9.8,
    "biofuel (%)": 0.1,
    "solar (%)": 0.0,
    "nuclear (MW)": 9960.0,
    "hydro (MW)": 2911.0,
    "gas (MW)": 2707.0,
    "wind (MW)": 1692.0,
    "biofuel (MW)": 21.0,
    "solar (MW)": 0.0
}