{
    "datetime": "2026-06-10T16:00:00-04:00",
    "Imports (MW)": 695.0,
    "Exports (MW)": 2257.0,
    "Net Import/Exports (MW)": 1562.0,
    "Power Generated (MW)": 22239.0,
    "Ontario Demand (MW)": 20677.0,
    "Total Emissions (tonnes)": 2431.0,
    "CO2e Intensity (g/kWh)": 109.0,
    "nuclear (%)": 42.6,
    "hydro (%)": 21.0,
    "gas (%)": 29.2,
    "wind (%)": 4.7,
    "biofuel (%)": 0.7,
    "solar (%)": 1.1,
    "nuclear (MW)": 9478.0,
    "hydro (MW)": 4664.0,
    "gas (MW)": 6485.0,
    "wind (MW)": 1054.0,
    "biofuel (MW)": 156.0,
    "solar (MW)": 245.0
}