{
    "datetime": "2024-03-26T02:00:00-04:00",
    "Imports (MW)": 47.0,
    "Exports (MW)": 2225.0,
    "Net Import/Exports (MW)": 2178.0,
    "Power Generated (MW)": 15251.0,
    "Ontario Demand (MW)": 13073.0,
    "Total Emissions (tonnes)": 239.0,
    "CO2e Intensity (g/kWh)": 16.0,
    "nuclear (%)": 48.6,
    "hydro (%)": 21.4,
    "gas (%)": 3.5,
    "wind (%)": 26.6,
    "biofuel (%)": 0.0,
    "solar (%)": 0.0,
    "nuclear (MW)": 7407.0,
    "hydro (MW)": 3261.0,
    "gas (MW)": 527.0,
    "wind (MW)": 4056.0,
    "biofuel (MW)": 0.0,
    "solar (MW)": 0.0
}