{
    "datetime": "2023-12-30T07:00:00-05:00",
    "Imports (MW)": 9.0,
    "Exports (MW)": 1787.0,
    "Net Import/Exports (MW)": 1778.0,
    "Power Generated (MW)": 16246.0,
    "Ontario Demand (MW)": 14468.0,
    "Total Emissions (tonnes)": 794.0,
    "CO2e Intensity (g/kWh)": 49.0,
    "nuclear (%)": 58.3,
    "hydro (%)": 28.1,
    "gas (%)": 10.5,
    "wind (%)": 2.9,
    "biofuel (%)": 0.1,
    "solar (%)": 0.0,
    "nuclear (MW)": 9476.0,
    "hydro (MW)": 4566.0,
    "gas (MW)": 1712.0,
    "wind (MW)": 476.0,
    "biofuel (MW)": 16.0,
    "solar (MW)": 0.0
}