{
    "datetime": "2024-08-17T00:00:00-04:00",
    "Imports (MW)": 9.0,
    "Exports (MW)": 2606.0,
    "Net Import/Exports (MW)": 2597.0,
    "Power Generated (MW)": 19516.0,
    "Ontario Demand (MW)": 16919.0,
    "Total Emissions (tonnes)": 1725.0,
    "CO2e Intensity (g/kWh)": 88.0,
    "nuclear (%)": 52.8,
    "hydro (%)": 19.0,
    "gas (%)": 24.3,
    "wind (%)": 3.4,
    "biofuel (%)": 0.4,
    "solar (%)": 0.0,
    "nuclear (MW)": 10304.0,
    "hydro (MW)": 3715.0,
    "gas (MW)": 4743.0,
    "wind (MW)": 670.0,
    "biofuel (MW)": 84.0,
    "solar (MW)": 0.0
}