{
    "datetime": "2023-12-22T18:00:00-05:00",
    "Imports (MW)": 13.0,
    "Exports (MW)": 3136.0,
    "Net Import/Exports (MW)": 3123.0,
    "Power Generated (MW)": 21328.0,
    "Ontario Demand (MW)": 18205.0,
    "Total Emissions (tonnes)": 1836.0,
    "CO2e Intensity (g/kWh)": 86.0,
    "nuclear (%)": 45.5,
    "hydro (%)": 24.6,
    "gas (%)": 24.6,
    "wind (%)": 4.9,
    "biofuel (%)": 0.3,
    "solar (%)": 0.0,
    "nuclear (MW)": 9704.0,
    "hydro (MW)": 5251.0,
    "gas (MW)": 5251.0,
    "wind (MW)": 1048.0,
    "biofuel (MW)": 74.0,
    "solar (MW)": 0.0
}