{
    "datetime": "2026-07-07T13:00:00-04:00",
    "Imports (MW)": 741.0,
    "Exports (MW)": 2155.0,
    "Net Import/Exports (MW)": 1414.0,
    "Power Generated (MW)": 21510.0,
    "Ontario Demand (MW)": 20096.0,
    "Total Emissions (tonnes)": 2360.0,
    "CO2e Intensity (g/kWh)": 110.0,
    "nuclear (%)": 47.8,
    "hydro (%)": 20.4,
    "gas (%)": 29.8,
    "wind (%)": 0.5,
    "biofuel (%)": 0.3,
    "solar (%)": 1.3,
    "nuclear (MW)": 10273.0,
    "hydro (MW)": 4391.0,
    "gas (MW)": 6405.0,
    "wind (MW)": 102.0,
    "biofuel (MW)": 59.0,
    "solar (MW)": 275.0
}