{
    "datetime": "2025-08-16T14:00:00-04:00",
    "Imports (MW)": 1105.0,
    "Exports (MW)": 383.0,
    "Net Import/Exports (MW)": -722.0,
    "Power Generated (MW)": 20346.0,
    "Ontario Demand (MW)": 21068.0,
    "Total Emissions (tonnes)": 2157.0,
    "CO2e Intensity (g/kWh)": 106.0,
    "nuclear (%)": 45.7,
    "hydro (%)": 21.5,
    "gas (%)": 29.2,
    "wind (%)": 1.2,
    "biofuel (%)": 0.4,
    "solar (%)": 1.8,
    "nuclear (MW)": 9303.0,
    "hydro (MW)": 4377.0,
    "gas (MW)": 5932.0,
    "wind (MW)": 240.0,
    "biofuel (MW)": 82.0,
    "solar (MW)": 370.0
}