{
    "datetime": "2024-02-02T16:00:00-05:00",
    "Imports (MW)": 10.0,
    "Exports (MW)": 3099.0,
    "Net Import/Exports (MW)": 3089.0,
    "Power Generated (MW)": 20382.0,
    "Ontario Demand (MW)": 17293.0,
    "Total Emissions (tonnes)": 1768.0,
    "CO2e Intensity (g/kWh)": 87.0,
    "nuclear (%)": 49.3,
    "hydro (%)": 22.6,
    "gas (%)": 23.9,
    "wind (%)": 3.6,
    "biofuel (%)": 0.4,
    "solar (%)": 0.2,
    "nuclear (MW)": 10045.0,
    "hydro (MW)": 4601.0,
    "gas (MW)": 4873.0,
    "wind (MW)": 743.0,
    "biofuel (MW)": 79.0,
    "solar (MW)": 41.0
}