{
    "datetime": "2023-12-07T06:00:00-05:00",
    "Imports (MW)": 9.0,
    "Exports (MW)": 3103.0,
    "Net Import/Exports (MW)": 3094.0,
    "Power Generated (MW)": 19722.0,
    "Ontario Demand (MW)": 16628.0,
    "Total Emissions (tonnes)": 1056.0,
    "CO2e Intensity (g/kWh)": 54.0,
    "nuclear (%)": 46.6,
    "hydro (%)": 22.4,
    "gas (%)": 15.8,
    "wind (%)": 15.1,
    "biofuel (%)": 0.0,
    "solar (%)": 0.0,
    "nuclear (MW)": 9188.0,
    "hydro (MW)": 4426.0,
    "gas (MW)": 3121.0,
    "wind (MW)": 2983.0,
    "biofuel (MW)": 4.0,
    "solar (MW)": 0.0
}