{
    "datetime": "2024-07-14T17:00:00-04:00",
    "Imports (MW)": 1229.0,
    "Exports (MW)": 2475.0,
    "Net Import/Exports (MW)": 1246.0,
    "Power Generated (MW)": 20602.0,
    "Ontario Demand (MW)": 19356.0,
    "Total Emissions (tonnes)": 1591.0,
    "CO2e Intensity (g/kWh)": 77.0,
    "nuclear (%)": 45.0,
    "hydro (%)": 23.9,
    "gas (%)": 19.8,
    "wind (%)": 9.9,
    "biofuel (%)": 0.1,
    "solar (%)": 1.3,
    "nuclear (MW)": 9277.0,
    "hydro (MW)": 4924.0,
    "gas (MW)": 4069.0,
    "wind (MW)": 2035.0,
    "biofuel (MW)": 30.0,
    "solar (MW)": 267.0
}