{
    "datetime": "2023-09-04T15:00:00-04:00",
    "Imports (MW)": 1288.0,
    "Exports (MW)": 1391.0,
    "Net Import/Exports (MW)": 103.0,
    "Power Generated (MW)": 20454.0,
    "Ontario Demand (MW)": 20351.0,
    "Total Emissions (tonnes)": 1894.0,
    "CO2e Intensity (g/kWh)": 93.0,
    "nuclear (%)": 46.6,
    "hydro (%)": 19.3,
    "gas (%)": 26.1,
    "wind (%)": 5.5,
    "biofuel (%)": 0.4,
    "solar (%)": 2.0,
    "nuclear (MW)": 9537.0,
    "hydro (MW)": 3949.0,
    "gas (MW)": 5346.0,
    "wind (MW)": 1131.0,
    "biofuel (MW)": 89.0,
    "solar (MW)": 402.0
}