{
    "datetime": "2025-03-10T13:00:00-04:00",
    "Imports (MW)": 37.0,
    "Exports (MW)": 1415.0,
    "Net Import/Exports (MW)": 1378.0,
    "Power Generated (MW)": 17032.0,
    "Ontario Demand (MW)": 15654.0,
    "Total Emissions (tonnes)": 992.0,
    "CO2e Intensity (g/kWh)": 58.0,
    "nuclear (%)": 51.6,
    "hydro (%)": 24.5,
    "gas (%)": 15.7,
    "wind (%)": 5.4,
    "biofuel (%)": 0.4,
    "solar (%)": 2.4,
    "nuclear (MW)": 8797.0,
    "hydro (MW)": 4171.0,
    "gas (MW)": 2676.0,
    "wind (MW)": 921.0,
    "biofuel (MW)": 60.0,
    "solar (MW)": 407.0
}