{
    "datetime": "2024-12-10T06:00:00-05:00",
    "Imports (MW)": 16.0,
    "Exports (MW)": 2976.0,
    "Net Import/Exports (MW)": 2960.0,
    "Power Generated (MW)": 19386.0,
    "Ontario Demand (MW)": 16426.0,
    "Total Emissions (tonnes)": 1536.0,
    "CO2e Intensity (g/kWh)": 79.0,
    "nuclear (%)": 51.7,
    "hydro (%)": 21.9,
    "gas (%)": 21.8,
    "wind (%)": 4.3,
    "biofuel (%)": 0.4,
    "solar (%)": 0.0,
    "nuclear (MW)": 10016.0,
    "hydro (MW)": 4247.0,
    "gas (MW)": 4223.0,
    "wind (MW)": 828.0,
    "biofuel (MW)": 72.0,
    "solar (MW)": 0.0
}