{
    "datetime": "2024-04-14T23:00:00-04:00",
    "Imports (MW)": 9.0,
    "Exports (MW)": 2099.0,
    "Net Import/Exports (MW)": 2090.0,
    "Power Generated (MW)": 16033.0,
    "Ontario Demand (MW)": 13943.0,
    "Total Emissions (tonnes)": 635.0,
    "CO2e Intensity (g/kWh)": 40.0,
    "nuclear (%)": 46.5,
    "hydro (%)": 29.5,
    "gas (%)": 13.2,
    "wind (%)": 10.8,
    "biofuel (%)": 0.0,
    "solar (%)": 0.0,
    "nuclear (MW)": 7463.0,
    "hydro (MW)": 4732.0,
    "gas (MW)": 2111.0,
    "wind (MW)": 1727.0,
    "biofuel (MW)": 0.0,
    "solar (MW)": 0.0
}