{
    "datetime": "2024-11-08T11:00:00-05:00",
    "Imports (MW)": 9.0,
    "Exports (MW)": 2764.0,
    "Net Import/Exports (MW)": 2755.0,
    "Power Generated (MW)": 18218.0,
    "Ontario Demand (MW)": 15463.0,
    "Total Emissions (tonnes)": 472.0,
    "CO2e Intensity (g/kWh)": 26.0,
    "nuclear (%)": 47.3,
    "hydro (%)": 26.5,
    "gas (%)": 6.7,
    "wind (%)": 18.4,
    "biofuel (%)": 0.1,
    "solar (%)": 1.0,
    "nuclear (MW)": 8623.0,
    "hydro (MW)": 4823.0,
    "gas (MW)": 1225.0,
    "wind (MW)": 3346.0,
    "biofuel (MW)": 19.0,
    "solar (MW)": 182.0
}