{
    "datetime": "2024-12-23T23:00:00-05:00",
    "Imports (MW)": 121.0,
    "Exports (MW)": 3146.0,
    "Net Import/Exports (MW)": 3025.0,
    "Power Generated (MW)": 19151.0,
    "Ontario Demand (MW)": 16126.0,
    "Total Emissions (tonnes)": 994.0,
    "CO2e Intensity (g/kWh)": 52.0,
    "nuclear (%)": 57.0,
    "hydro (%)": 19.2,
    "gas (%)": 12.9,
    "wind (%)": 10.4,
    "biofuel (%)": 0.5,
    "solar (%)": 0.0,
    "nuclear (MW)": 10909.0,
    "hydro (MW)": 3677.0,
    "gas (MW)": 2477.0,
    "wind (MW)": 1999.0,
    "biofuel (MW)": 89.0,
    "solar (MW)": 0.0
}