{
    "datetime": "2025-11-06T04:00:00-05:00",
    "Imports (MW)": 67.0,
    "Exports (MW)": 1889.0,
    "Net Import/Exports (MW)": 1822.0,
    "Power Generated (MW)": 15973.0,
    "Ontario Demand (MW)": 14151.0,
    "Total Emissions (tonnes)": 1198.0,
    "CO2e Intensity (g/kWh)": 75.0,
    "nuclear (%)": 46.4,
    "hydro (%)": 20.0,
    "gas (%)": 17.7,
    "wind (%)": 15.6,
    "biofuel (%)": 0.3,
    "solar (%)": 0.0,
    "nuclear (MW)": 7415.0,
    "hydro (MW)": 3196.0,
    "gas (MW)": 2825.0,
    "wind (MW)": 2486.0,
    "biofuel (MW)": 51.0,
    "solar (MW)": 0.0
}