{
    "datetime": "2025-08-13T21:00:00-04:00",
    "Imports (MW)": 1474.0,
    "Exports (MW)": 914.0,
    "Net Import/Exports (MW)": -560.0,
    "Power Generated (MW)": 21879.0,
    "Ontario Demand (MW)": 22439.0,
    "Total Emissions (tonnes)": 2500.0,
    "CO2e Intensity (g/kWh)": 114.0,
    "nuclear (%)": 42.8,
    "hydro (%)": 22.7,
    "gas (%)": 30.6,
    "wind (%)": 3.3,
    "biofuel (%)": 0.1,
    "solar (%)": 0.0,
    "nuclear (MW)": 9355.0,
    "hydro (MW)": 4968.0,
    "gas (MW)": 6698.0,
    "wind (MW)": 720.0,
    "biofuel (MW)": 27.0,
    "solar (MW)": 0.0
}