{
    "datetime": "2024-10-26T14:00:00-04:00",
    "Imports (MW)": 9.0,
    "Exports (MW)": 1641.0,
    "Net Import/Exports (MW)": 1632.0,
    "Power Generated (MW)": 15394.0,
    "Ontario Demand (MW)": 13762.0,
    "Total Emissions (tonnes)": 483.0,
    "CO2e Intensity (g/kWh)": 31.0,
    "nuclear (%)": 50.8,
    "hydro (%)": 19.3,
    "gas (%)": 9.3,
    "wind (%)": 18.7,
    "biofuel (%)": 0.1,
    "solar (%)": 1.8,
    "nuclear (MW)": 7817.0,
    "hydro (MW)": 2964.0,
    "gas (MW)": 1431.0,
    "wind (MW)": 2883.0,
    "biofuel (MW)": 19.0,
    "solar (MW)": 280.0
}