{
    "datetime": "2026-06-02T06:00:00-04:00",
    "Imports (MW)": 9.0,
    "Exports (MW)": 3093.0,
    "Net Import/Exports (MW)": 3084.0,
    "Power Generated (MW)": 15968.0,
    "Ontario Demand (MW)": 12884.0,
    "Total Emissions (tonnes)": 397.0,
    "CO2e Intensity (g/kWh)": 25.0,
    "nuclear (%)": 59.9,
    "hydro (%)": 27.7,
    "gas (%)": 7.8,
    "wind (%)": 4.5,
    "biofuel (%)": 0.1,
    "solar (%)": 0.0,
    "nuclear (MW)": 9571.0,
    "hydro (MW)": 4424.0,
    "gas (MW)": 1242.0,
    "wind (MW)": 714.0,
    "biofuel (MW)": 15.0,
    "solar (MW)": 0.0
}