{
    "datetime": "2024-03-08T21:00:00-05:00",
    "Imports (MW)": 9.0,
    "Exports (MW)": 1710.0,
    "Net Import/Exports (MW)": 1701.0,
    "Power Generated (MW)": 16945.0,
    "Ontario Demand (MW)": 15244.0,
    "Total Emissions (tonnes)": 492.0,
    "CO2e Intensity (g/kWh)": 29.0,
    "nuclear (%)": 49.1,
    "hydro (%)": 22.8,
    "gas (%)": 10.2,
    "wind (%)": 17.4,
    "biofuel (%)": 0.4,
    "solar (%)": 0.0,
    "nuclear (MW)": 8316.0,
    "hydro (MW)": 3861.0,
    "gas (MW)": 1736.0,
    "wind (MW)": 2956.0,
    "biofuel (MW)": 76.0,
    "solar (MW)": 0.0
}