{
    "datetime": "2023-09-15T01:00:00-04:00",
    "Imports (MW)": 69.0,
    "Exports (MW)": 2190.0,
    "Net Import/Exports (MW)": 2121.0,
    "Power Generated (MW)": 14924.0,
    "Ontario Demand (MW)": 12803.0,
    "Total Emissions (tonnes)": 672.0,
    "CO2e Intensity (g/kWh)": 45.0,
    "nuclear (%)": 65.5,
    "hydro (%)": 22.5,
    "gas (%)": 10.0,
    "wind (%)": 1.7,
    "biofuel (%)": 0.3,
    "solar (%)": 0.0,
    "nuclear (MW)": 9782.0,
    "hydro (MW)": 3351.0,
    "gas (MW)": 1485.0,
    "wind (MW)": 261.0,
    "biofuel (MW)": 45.0,
    "solar (MW)": 0.0
}