{
    "datetime": "2024-03-01T01:00:00-05:00",
    "Imports (MW)": 77.0,
    "Exports (MW)": 2463.0,
    "Net Import/Exports (MW)": 2386.0,
    "Power Generated (MW)": 17453.0,
    "Ontario Demand (MW)": 15067.0,
    "Total Emissions (tonnes)": 1247.0,
    "CO2e Intensity (g/kWh)": 71.0,
    "nuclear (%)": 47.5,
    "hydro (%)": 22.4,
    "gas (%)": 22.2,
    "wind (%)": 7.6,
    "biofuel (%)": 0.2,
    "solar (%)": 0.0,
    "nuclear (MW)": 8283.0,
    "hydro (MW)": 3917.0,
    "gas (MW)": 3875.0,
    "wind (MW)": 1335.0,
    "biofuel (MW)": 43.0,
    "solar (MW)": 0.0
}