{
    "datetime": "2024-10-24T21:00:00-04:00",
    "Imports (MW)": 152.0,
    "Exports (MW)": 1294.0,
    "Net Import/Exports (MW)": 1142.0,
    "Power Generated (MW)": 17834.0,
    "Ontario Demand (MW)": 16692.0,
    "Total Emissions (tonnes)": 1290.0,
    "CO2e Intensity (g/kWh)": 72.0,
    "nuclear (%)": 48.4,
    "hydro (%)": 26.9,
    "gas (%)": 22.3,
    "wind (%)": 1.9,
    "biofuel (%)": 0.5,
    "solar (%)": 0.0,
    "nuclear (MW)": 8625.0,
    "hydro (MW)": 4794.0,
    "gas (MW)": 3983.0,
    "wind (MW)": 343.0,
    "biofuel (MW)": 89.0,
    "solar (MW)": 0.0
}