{
    "datetime": "2026-02-22T14:00:00-05:00",
    "Imports (MW)": 659.0,
    "Exports (MW)": 3202.0,
    "Net Import/Exports (MW)": 2543.0,
    "Power Generated (MW)": 19502.0,
    "Ontario Demand (MW)": 16959.0,
    "Total Emissions (tonnes)": 2207.0,
    "CO2e Intensity (g/kWh)": 113.0,
    "nuclear (%)": 45.1,
    "hydro (%)": 20.4,
    "gas (%)": 31.2,
    "wind (%)": 2.7,
    "biofuel (%)": 0.1,
    "solar (%)": 0.4,
    "nuclear (MW)": 8802.0,
    "hydro (MW)": 3976.0,
    "gas (MW)": 6089.0,
    "wind (MW)": 528.0,
    "biofuel (MW)": 11.0,
    "solar (MW)": 86.0
}