{
    "datetime": "2025-08-08T00:00:00-04:00",
    "Imports (MW)": 90.0,
    "Exports (MW)": 1320.0,
    "Net Import/Exports (MW)": 1230.0,
    "Power Generated (MW)": 19571.0,
    "Ontario Demand (MW)": 18341.0,
    "Total Emissions (tonnes)": 2026.0,
    "CO2e Intensity (g/kWh)": 104.0,
    "nuclear (%)": 47.8,
    "hydro (%)": 17.4,
    "gas (%)": 29.2,
    "wind (%)": 5.0,
    "biofuel (%)": 0.6,
    "solar (%)": 0.0,
    "nuclear (MW)": 9354.0,
    "hydro (MW)": 3399.0,
    "gas (MW)": 5713.0,
    "wind (MW)": 986.0,
    "biofuel (MW)": 119.0,
    "solar (MW)": 0.0
}