{
    "datetime": "2024-06-22T06:00:00-04:00",
    "Imports (MW)": 9.0,
    "Exports (MW)": 2034.0,
    "Net Import/Exports (MW)": 2025.0,
    "Power Generated (MW)": 15613.0,
    "Ontario Demand (MW)": 13588.0,
    "Total Emissions (tonnes)": 875.0,
    "CO2e Intensity (g/kWh)": 56.0,
    "nuclear (%)": 65.8,
    "hydro (%)": 20.5,
    "gas (%)": 13.4,
    "wind (%)": 0.2,
    "biofuel (%)": 0.1,
    "solar (%)": 0.0,
    "nuclear (MW)": 10268.0,
    "hydro (MW)": 3208.0,
    "gas (MW)": 2086.0,
    "wind (MW)": 33.0,
    "biofuel (MW)": 18.0,
    "solar (MW)": 0.0
}