{
    "datetime": "2024-02-25T15:00:00-05:00",
    "Imports (MW)": 9.0,
    "Exports (MW)": 3003.0,
    "Net Import/Exports (MW)": 2994.0,
    "Power Generated (MW)": 18258.0,
    "Ontario Demand (MW)": 15264.0,
    "Total Emissions (tonnes)": 477.0,
    "CO2e Intensity (g/kWh)": 26.0,
    "nuclear (%)": 45.7,
    "hydro (%)": 22.0,
    "gas (%)": 9.3,
    "wind (%)": 21.9,
    "biofuel (%)": 0.2,
    "solar (%)": 1.0,
    "nuclear (MW)": 8340.0,
    "hydro (MW)": 4010.0,
    "gas (MW)": 1689.0,
    "wind (MW)": 3995.0,
    "biofuel (MW)": 40.0,
    "solar (MW)": 184.0
}