{
    "datetime": "2024-08-09T12:00:00-04:00",
    "Imports (MW)": 1025.0,
    "Exports (MW)": 672.0,
    "Net Import/Exports (MW)": -353.0,
    "Power Generated (MW)": 18508.0,
    "Ontario Demand (MW)": 18861.0,
    "Total Emissions (tonnes)": 1793.0,
    "CO2e Intensity (g/kWh)": 97.0,
    "nuclear (%)": 46.8,
    "hydro (%)": 20.5,
    "gas (%)": 26.6,
    "wind (%)": 5.1,
    "biofuel (%)": 0.2,
    "solar (%)": 0.9,
    "nuclear (MW)": 8670.0,
    "hydro (MW)": 3785.0,
    "gas (MW)": 4931.0,
    "wind (MW)": 936.0,
    "biofuel (MW)": 28.0,
    "solar (MW)": 158.0
}