{
    "datetime": "2024-03-03T08:00:00-05:00",
    "Imports (MW)": 10.0,
    "Exports (MW)": 1970.0,
    "Net Import/Exports (MW)": 1960.0,
    "Power Generated (MW)": 16321.0,
    "Ontario Demand (MW)": 14361.0,
    "Total Emissions (tonnes)": 708.0,
    "CO2e Intensity (g/kWh)": 43.0,
    "nuclear (%)": 51.1,
    "hydro (%)": 27.7,
    "gas (%)": 14.6,
    "wind (%)": 6.2,
    "biofuel (%)": 0.1,
    "solar (%)": 0.2,
    "nuclear (MW)": 8341.0,
    "hydro (MW)": 4523.0,
    "gas (MW)": 2389.0,
    "wind (MW)": 1011.0,
    "biofuel (MW)": 22.0,
    "solar (MW)": 35.0
}