{
    "datetime": "2024-12-22T18:00:00-05:00",
    "Imports (MW)": 1031.0,
    "Exports (MW)": 3715.0,
    "Net Import/Exports (MW)": 2684.0,
    "Power Generated (MW)": 23168.0,
    "Ontario Demand (MW)": 20484.0,
    "Total Emissions (tonnes)": 2035.0,
    "CO2e Intensity (g/kWh)": 88.0,
    "nuclear (%)": 47.1,
    "hydro (%)": 24.4,
    "gas (%)": 23.7,
    "wind (%)": 4.5,
    "biofuel (%)": 0.2,
    "solar (%)": 0.0,
    "nuclear (MW)": 10912.0,
    "hydro (MW)": 5656.0,
    "gas (MW)": 5502.0,
    "wind (MW)": 1044.0,
    "biofuel (MW)": 54.0,
    "solar (MW)": 0.0
}