{
    "datetime": "2023-07-16T08:00:00-04:00",
    "Imports (MW)": 9.0,
    "Exports (MW)": 2428.0,
    "Net Import/Exports (MW)": 2419.0,
    "Power Generated (MW)": 15594.0,
    "Ontario Demand (MW)": 13175.0,
    "Total Emissions (tonnes)": 917.0,
    "CO2e Intensity (g/kWh)": 59.0,
    "nuclear (%)": 65.1,
    "hydro (%)": 19.6,
    "gas (%)": 13.4,
    "wind (%)": 1.5,
    "biofuel (%)": 0.2,
    "solar (%)": 0.2,
    "nuclear (MW)": 10146.0,
    "hydro (MW)": 3059.0,
    "gas (MW)": 2094.0,
    "wind (MW)": 239.0,
    "biofuel (MW)": 31.0,
    "solar (MW)": 25.0
}