{
    "datetime": "2025-12-13T14:00:00-05:00",
    "Imports (MW)": 321.0,
    "Exports (MW)": 3277.0,
    "Net Import/Exports (MW)": 2956.0,
    "Power Generated (MW)": 21478.0,
    "Ontario Demand (MW)": 18522.0,
    "Total Emissions (tonnes)": 1970.0,
    "CO2e Intensity (g/kWh)": 92.0,
    "nuclear (%)": 40.7,
    "hydro (%)": 18.0,
    "gas (%)": 25.1,
    "wind (%)": 15.9,
    "biofuel (%)": 0.1,
    "solar (%)": 0.1,
    "nuclear (MW)": 8744.0,
    "hydro (MW)": 3875.0,
    "gas (MW)": 5400.0,
    "wind (MW)": 3421.0,
    "biofuel (MW)": 14.0,
    "solar (MW)": 24.0
}