{
    "datetime": "2025-06-09T10:00:00-04:00",
    "Imports (MW)": 9.0,
    "Exports (MW)": 2072.0,
    "Net Import/Exports (MW)": 2063.0,
    "Power Generated (MW)": 17879.0,
    "Ontario Demand (MW)": 15816.0,
    "Total Emissions (tonnes)": 731.0,
    "CO2e Intensity (g/kWh)": 41.0,
    "nuclear (%)": 53.5,
    "hydro (%)": 26.5,
    "gas (%)": 13.6,
    "wind (%)": 5.6,
    "biofuel (%)": 0.4,
    "solar (%)": 0.3,
    "nuclear (MW)": 9574.0,
    "hydro (MW)": 4744.0,
    "gas (MW)": 2433.0,
    "wind (MW)": 1008.0,
    "biofuel (MW)": 66.0,
    "solar (MW)": 54.0
}