{
    "datetime": "2025-06-06T20:00:00-04:00",
    "Imports (MW)": 11.0,
    "Exports (MW)": 2780.0,
    "Net Import/Exports (MW)": 2769.0,
    "Power Generated (MW)": 20017.0,
    "Ontario Demand (MW)": 17248.0,
    "Total Emissions (tonnes)": 1405.0,
    "CO2e Intensity (g/kWh)": 70.0,
    "nuclear (%)": 47.8,
    "hydro (%)": 28.5,
    "gas (%)": 19.8,
    "wind (%)": 3.4,
    "biofuel (%)": 0.1,
    "solar (%)": 0.2,
    "nuclear (MW)": 9570.0,
    "hydro (MW)": 5702.0,
    "gas (MW)": 3958.0,
    "wind (MW)": 684.0,
    "biofuel (MW)": 23.0,
    "solar (MW)": 48.0
}