{
    "datetime": "2024-03-06T17:00:00-05:00",
    "Imports (MW)": 9.0,
    "Exports (MW)": 2056.0,
    "Net Import/Exports (MW)": 2047.0,
    "Power Generated (MW)": 18875.0,
    "Ontario Demand (MW)": 16828.0,
    "Total Emissions (tonnes)": 1010.0,
    "CO2e Intensity (g/kWh)": 53.0,
    "nuclear (%)": 44.2,
    "hydro (%)": 24.3,
    "gas (%)": 15.6,
    "wind (%)": 15.5,
    "biofuel (%)": 0.4,
    "solar (%)": 0.1,
    "nuclear (MW)": 8340.0,
    "hydro (MW)": 4581.0,
    "gas (MW)": 2939.0,
    "wind (MW)": 2928.0,
    "biofuel (MW)": 74.0,
    "solar (MW)": 13.0
}