{
    "datetime": "2026-02-18T10:00:00-05:00",
    "Imports (MW)": 295.0,
    "Exports (MW)": 3509.0,
    "Net Import/Exports (MW)": 3214.0,
    "Power Generated (MW)": 22052.0,
    "Ontario Demand (MW)": 18838.0,
    "Total Emissions (tonnes)": 2283.0,
    "CO2e Intensity (g/kWh)": 104.0,
    "nuclear (%)": 37.6,
    "hydro (%)": 19.4,
    "gas (%)": 28.2,
    "wind (%)": 14.2,
    "biofuel (%)": 0.1,
    "solar (%)": 0.2,
    "nuclear (MW)": 8295.0,
    "hydro (MW)": 4273.0,
    "gas (MW)": 6213.0,
    "wind (MW)": 3132.0,
    "biofuel (MW)": 28.0,
    "solar (MW)": 52.0
}