{
    "datetime": "2026-02-22T13:00:00-05:00",
    "Imports (MW)": 585.0,
    "Exports (MW)": 2873.0,
    "Net Import/Exports (MW)": 2288.0,
    "Power Generated (MW)": 19197.0,
    "Ontario Demand (MW)": 16909.0,
    "Total Emissions (tonnes)": 2212.0,
    "CO2e Intensity (g/kWh)": 115.0,
    "nuclear (%)": 45.9,
    "hydro (%)": 19.1,
    "gas (%)": 31.6,
    "wind (%)": 2.3,
    "biofuel (%)": 0.1,
    "solar (%)": 0.5,
    "nuclear (MW)": 8805.0,
    "hydro (MW)": 3672.0,
    "gas (MW)": 6073.0,
    "wind (MW)": 442.0,
    "biofuel (MW)": 14.0,
    "solar (MW)": 105.0
}