{
    "datetime": "2024-12-16T18:00:00-05:00",
    "production_by_plant": {
        "BRUCEA-G1": 826.0,
        "BRUCEA-G2": 821.0,
        "BRUCEA-G3": 0.0,
        "BRUCEA-G4": 800.0,
        "BRUCEB-G5": 824.0,
        "BRUCEB-G6": 823.0,
        "BRUCEB-G7": 817.0,
        "BRUCEB-G8": 816.0,
        "DARLINGTON-G1": 211.0,
        "DARLINGTON-G2": 873.0,
        "DARLINGTON-G3": 862.0,
        "DARLINGTON-G4": 0.0,
        "PICKERINGA-G1": 0.0,
        "PICKERINGA-G4": 514.0,
        "PICKERINGB-G5": 518.0,
        "PICKERINGB-G6": 497.0,
        "PICKERINGB-G7": 527.0,
        "PICKERINGB-G8": 524.0,
        "BRIGHTON BEACH": 0.0,
        "CARDINAL": 0.0,
        "COCHRANECGS": 0.0,
        "DESTEC": 0.0,
        "DOWCHEMICAL": 19.0,
        "DPNTMTLND": 26.0,
        "EAST WINDSOR-G1": 0.0,
        "EAST WINDSOR-G2": 0.0,
        "GREENFIELD ENERGY CENTRE-G1": 131.0,
        "GREENFIELD ENERGY CENTRE-G2": 131.0,
        "GREENFIELD ENERGY CENTRE-G3": 0.0,
        "GREENFIELD ENERGY CENTRE-G4": 157.0,
        "GREENFIELD SOUTH-G1": 0.0,
        "GREENFIELD SOUTH-G2": 0.0,
        "GTAA-G1": 0.0,
        "GTAA-G2": 0.0,
        "GTAA-G3": 0.0,
        "HALTONHILLS-LT.G1": 166.0,
        "HALTONHILLS-LT.G2": 166.0,
        "HALTONHILLS-LT.G3": 202.0,
        "KAPGS": 0.0,
        "LAKESUPERIOR": 0.0,
        "LENNOX-G1": 0.0,
        "LENNOX-G2": 0.0,
        "LENNOX-G3": 0.0,
        "LENNOX-G4": 31.0,
        "NAPANEE-G1": 215.0,
        "NAPANEE-G2": 260.0,
        "NAPANEE-G3": 256.0,
        "NIPIGONGS": 0.0,
        "NORTHBAYGS": 0.0,
        "NPIROQFALLS": 0.0,
        "NPKIRKLAND-G1-G5": 24.0,
        "NPKIRKLAND-G6": 0.0,
        "PORTLANDS-G1": 122.0,
        "PORTLANDS-G2": 121.0,
        "PORTLANDS-G3": 158.0,
        "SITHE GOREWAY-G11": 0.0,
        "SITHE GOREWAY-G12": 60.0,
        "SITHE GOREWAY-G13": 59.0,
        "SITHE GOREWAY-G15": 110.0,
        "STCLAIRCGS": 451.0,
        "TAOHSC": 0.0,
        "TASARNIA": 220.0,
        "TAWINDSOR": 0.0,
        "THOROLDCGS": 0.0,
        "TUNISGS": 0.0,
        "WESTWINDSOR": 68.0,
        "WHITBYCGS": 0.0,
        "YORKCGS-G1": 0.0,
        "YORKCGS-G2": 0.0,
        "ABKENORA": 13.0,
        "AGUASABON": 21.0,
        "ALEXANDER": 41.0,
        "APIROQUOIS": 82.0,
        "ARNPRIOR": 38.0,
        "AUBREYFALLS": 44.0,
        "BARRETT": 78.0,
        "BECK1": 223.0,
        "BECK2": 1068.0,
        "BECK2 PGS": 3.0,
        "CAMERONFALLS": 50.0,
        "CANYON": 235.0,
        "CARIBOUFALLS": 59.0,
        "CARMICHAEL": 9.0,
        "CHATSFALLS": 91.0,
        "CHENAUX": 112.0,
        "CLERGUE": 34.0,
        "DA WATSON": 63.0,
        "DECEWFALLS": 85.0,
        "DECEWND1": 9.0,
        "DESJOACHIMS": 397.0,
        "EARFALLS": 16.0,
        "FORTFRANCSWC": 4.0,
        "GARTSHORE": 78.0,
        "HARMON": 0.0,
        "HARMON 2": 77.0,
        "HARRIS": 3.0,
        "HOLDEN": 191.0,
        "HOLINGSWTH": 21.0,
        "KAKABEKA": 12.0,
        "KIPLING": 73.0,
        "KIPLING 2": 0.0,
        "LITTLELONG": 64.0,
        "LITTLELONG 2": 0.0,
        "LONGSAULTE": 14.0,
        "LOWER WHITE RIVER": 4.0,
        "LOWERNOTCH": 110.0,
        "MACKAYGS": 49.0,
        "MANITOUFALLS": 39.0,
        "MISSION": 3.0,
        "MTNCHUTE": 73.0,
        "NAGAGAMI": 3.0,
        "OTTERRAPIDS": 106.0,
        "PETER SUTHERLAND SR": 12.0,
        "PINEPORTAGE": 1.0,
        "RAYNER": 14.0,
        "REDROCK": 11.0,
        "SAUNDERS": 724.0,
        "SILVERFALLS": 47.0,
        "SMOKY 2": 82.0,
        "STEEPHILL": 2.0,
        "STEWARTVLE": 50.0,
        "UMBATAFALLS": 9.0,
        "UPPER WHITE RIVER": 4.0,
        "WELLS": 70.0,
        "WHITEDOG": 40.0,
        "ADELAIDE": 39.0,
        "AMARANTH": 105.0,
        "AMHERST ISLAND": 73.0,
        "ARMOW": 166.0,
        "BELLE RIVER": 87.0,
        "BLAKE": 54.0,
        "BORNISH": 53.0,
        "BOW LAKE": 11.0,
        "BOW LAKE 2": 22.0,
        "CEDAR POINT 2": 93.0,
        "COMBER": 144.0,
        "CRYSLER": 58.0,
        "DILLON": 73.0,
        "EAST LAKE": 72.0,
        "ERIEAU": 90.0,
        "GOSFIELDWGS": 46.0,
        "GOSHEN": 88.0,
        "GOULAIS": 8.0,
        "GRAND VALLEY 3": 37.0,
        "GRANDWF": 88.0,
        "GREENWICH": 5.0,
        "HENVEY NORTH": 101.0,
        "HENVEY SOUTH": 160.0,
        "JERICHO": 118.0,
        "K2WIND": 257.0,
        "KINGSBRIDGE": 31.0,
        "LANDON": 29.0,
        "MCLEANSMTNWF-LT.AG_T1": 0.0,
        "NORTH KENT": 69.0,
        "PAROCHES": 37.0,
        "PORT BURWELL": 66.0,
        "PORTALMA-T1": 93.0,
        "PORTALMA-T3": 97.0,
        "PRINCEFARM": 36.0,
        "RAILBEDWF-LT.AG_SR": 224.0,
        "RIPLEY SOUTH": 67.0,
        "ROMNEY": 41.0,
        "SANDUSK-LT.AG_T1": 51.0,
        "SHANNON": 60.0,
        "SPENCE": 94.0,
        "SUMMERHAVEN": 44.0,
        "UNDERWOOD": 133.0,
        "WEST LINCOLN NRWF": 106.0,
        "WOLFE ISLAND": 146.0,
        "ZURICH": 86.0,
        "GRANDSF": 0.0,
        "KINGSTONSF": 0.0,
        "NANTICOKE SOLAR": 0.0,
        "NORTHLAND POWER SOLAR FACILITIES": 0.0,
        "SOUTHGATE SF": 0.0,
        "STONE MILLS SF": 0.0,
        "WINDSOR AIRPORT SF": 0.0,
        "ATIKOKAN-G1": 0.0,
        "CALSTOCKGS": 18.0,
        "TBAYBOWATER CTS": 0.0
    }
}