{
    "datetime": "2024-06-04T00:00:00-04:00",
    "production_by_plant": {
        "BRUCEA-G1": 0.0,
        "BRUCEA-G2": 824.0,
        "BRUCEA-G3": 0.0,
        "BRUCEA-G4": 788.0,
        "BRUCEB-G5": 819.0,
        "BRUCEB-G6": 823.0,
        "BRUCEB-G7": 1.0,
        "BRUCEB-G8": 813.0,
        "DARLINGTON-G1": 0.0,
        "DARLINGTON-G2": 879.0,
        "DARLINGTON-G3": 804.0,
        "DARLINGTON-G4": 0.0,
        "PICKERINGA-G1": 521.0,
        "PICKERINGA-G4": 503.0,
        "PICKERINGB-G5": 0.0,
        "PICKERINGB-G6": 513.0,
        "PICKERINGB-G7": 0.0,
        "PICKERINGB-G8": 495.0,
        "BRIGHTON BEACH": 89.0,
        "CARDINAL": 0.0,
        "DESTEC": 0.0,
        "DOWCHEMICAL": 6.0,
        "DPNTMTLND": 0.0,
        "EAST WINDSOR-G1": 0.0,
        "EAST WINDSOR-G2": 0.0,
        "GREENFIELD ENERGY CENTRE-G1": 147.0,
        "GREENFIELD ENERGY CENTRE-G2": 148.0,
        "GREENFIELD ENERGY CENTRE-G3": 147.0,
        "GREENFIELD ENERGY CENTRE-G4": 368.0,
        "GREENFIELD SOUTH-G1": 115.0,
        "GREENFIELD SOUTH-G2": 73.0,
        "GTAA-G1": 0.0,
        "GTAA-G2": 0.0,
        "GTAA-G3": 0.0,
        "HALTONHILLS-LT.G1": 0.0,
        "HALTONHILLS-LT.G2": 0.0,
        "HALTONHILLS-LT.G3": 0.0,
        "KAPGS": 0.0,
        "LAKESUPERIOR": 0.0,
        "LENNOX-G1": 0.0,
        "LENNOX-G2": 2.0,
        "LENNOX-G3": 0.0,
        "LENNOX-G4": 0.0,
        "NAPANEE-G1": 0.0,
        "NAPANEE-G2": 0.0,
        "NAPANEE-G3": 0.0,
        "NIPIGONGS": 0.0,
        "NORTHBAYGS": 0.0,
        "NPCOCHRANE": 0.0,
        "NPIROQFALLS": 0.0,
        "NPKIRKLAND-G1-G5": 0.0,
        "NPKIRKLAND-G6": 0.0,
        "PORTLANDS-G1": 154.0,
        "PORTLANDS-G2": 158.0,
        "PORTLANDS-G3": 190.0,
        "SITHE GOREWAY-G11": 154.0,
        "SITHE GOREWAY-G12": 148.0,
        "SITHE GOREWAY-G13": 127.0,
        "SITHE GOREWAY-G15": 256.0,
        "STCLAIRCGS": 564.0,
        "TAOHSC": 0.0,
        "TASARNIA": 398.0,
        "TAWINDSOR": 0.0,
        "THOROLDCGS": 232.0,
        "TUNISGS": 0.0,
        "WESTWINDSOR": 0.0,
        "WHITBYCGS": 0.0,
        "YORKCGS-G1": 0.0,
        "YORKCGS-G2": 0.0,
        "ABKENORA": 14.0,
        "AGUASABON": 44.0,
        "ALEXANDER": 43.0,
        "APIROQUOIS": 67.0,
        "ARNPRIOR": 37.0,
        "AUBREYFALLS": 3.0,
        "BARRETT": 16.0,
        "BECK1": 476.0,
        "BECK2": 1077.0,
        "BECK2 PGS": 0.0,
        "CAMERONFALLS": 52.0,
        "CANYON": 165.0,
        "CARIBOUFALLS": 48.0,
        "CARMICHAEL": 11.0,
        "CHATSFALLS": 95.0,
        "CHENAUX": 51.0,
        "CLERGUE": 31.0,
        "DA WATSON": 30.0,
        "DECEWFALLS": 72.0,
        "DECEWND1": 10.0,
        "DESJOACHIMS": 56.0,
        "EARFALLS": 16.0,
        "FORTFRANCSWC": 4.0,
        "GARTSHORE": 17.0,
        "HARMON": 75.0,
        "HARMON 2": 0.0,
        "HARRIS": 2.0,
        "HOLDEN": 58.0,
        "HOLINGSWTH": 0.0,
        "KAKABEKA": 12.0,
        "KIPLING": 70.0,
        "KIPLING 2": 0.0,
        "LITTLELONG": 61.0,
        "LITTLELONG 2": 0.0,
        "LONGSAULTE": 14.0,
        "LOWER WHITE RIVER": 10.0,
        "LOWERNOTCH": 0.0,
        "MACKAYGS": 6.0,
        "MANITOUFALLS": 55.0,
        "MISSION": 1.0,
        "MTNCHUTE": 0.0,
        "NAGAGAMI": 13.0,
        "OTTERRAPIDS": 94.0,
        "PETER SUTHERLAND SR": 17.0,
        "PINEPORTAGE": 63.0,
        "RAYNER": 23.0,
        "REDROCK": 22.0,
        "SAUNDERS": 856.0,
        "SILVERFALLS": 0.0,
        "SMOKY 2": 82.0,
        "STEEPHILL": 3.0,
        "STEWARTVLE": 34.0,
        "UMBATAFALLS": 24.0,
        "UPPER WHITE RIVER": 8.0,
        "WELLS": 0.0,
        "WHITEDOG": 52.0,
        "ADELAIDE": 9.0,
        "AMARANTH": 5.0,
        "AMHERST ISLAND": 0.0,
        "ARMOW": 9.0,
        "BELLE RIVER": 18.0,
        "BLAKE": 5.0,
        "BORNISH": 10.0,
        "BOW LAKE": 9.0,
        "BOW LAKE 2": 10.0,
        "CEDAR POINT 2": 20.0,
        "COMBER": 22.0,
        "CRYSLER": 11.0,
        "DILLON": 13.0,
        "EAST LAKE": 10.0,
        "ERIEAU": 11.0,
        "GOSFIELDWGS": 6.0,
        "GOSHEN": 14.0,
        "GOULAIS": 16.0,
        "GRAND VALLEY 3": 6.0,
        "GRANDWF": 1.0,
        "GREENWICH": 0.0,
        "HENVEY NORTH": 0.0,
        "HENVEY SOUTH": 0.0,
        "JERICHO": 22.0,
        "K2WIND": 17.0,
        "KINGSBRIDGE": 2.0,
        "LANDON": 6.0,
        "MCLEANSMTNWF-LT.AG_T1": 13.0,
        "NORTH KENT": 12.0,
        "PAROCHES": 7.0,
        "PORT BURWELL": 0.0,
        "PORTALMA-T1": 18.0,
        "PORTALMA-T3": 21.0,
        "PRINCEFARM": 95.0,
        "RAILBEDWF-LT.AG_SR": 54.0,
        "RIPLEY SOUTH": 5.0,
        "ROMNEY": 20.0,
        "SANDUSK-LT.AG_T1": 5.0,
        "SHANNON": 3.0,
        "SPENCE": 8.0,
        "SUMMERHAVEN": 1.0,
        "UNDERWOOD": 6.0,
        "WEST LINCOLN NRWF": 1.0,
        "WOLFE ISLAND": 0.0,
        "ZURICH": 12.0,
        "GRANDSF": 0.0,
        "KINGSTONSF": 0.0,
        "NANTICOKE SOLAR": 0.0,
        "NORTHLAND POWER SOLAR FACILITIES": 0.0,
        "SOUTHGATE SF": 0.0,
        "STONE MILLS SF": 0.0,
        "WINDSOR AIRPORT SF": 0.0,
        "ATIKOKAN-G1": 0.0,
        "CALSTOCKGS": 20.0,
        "TBAYBOWATER CTS": 0.0
    }
}