{
    "datetime": "2024-04-12T06:00:00-04:00",
    "production_by_plant": {
        "BRUCEA-G1": 0.0,
        "BRUCEA-G2": 819.0,
        "BRUCEA-G3": 0.0,
        "BRUCEA-G4": 797.0,
        "BRUCEB-G5": 817.0,
        "BRUCEB-G6": 827.0,
        "BRUCEB-G7": 825.0,
        "BRUCEB-G8": 817.0,
        "DARLINGTON-G1": 0.0,
        "DARLINGTON-G2": 0.0,
        "DARLINGTON-G3": 0.0,
        "DARLINGTON-G4": 0.0,
        "PICKERINGA-G1": 520.0,
        "PICKERINGA-G4": 464.0,
        "PICKERINGB-G5": 534.0,
        "PICKERINGB-G6": 514.0,
        "PICKERINGB-G7": 0.0,
        "PICKERINGB-G8": 519.0,
        "BRIGHTON BEACH": 30.0,
        "CARDINAL": 0.0,
        "DESTEC": 0.0,
        "DOWCHEMICAL": 7.0,
        "DPNTMTLND": 0.0,
        "EAST WINDSOR-G1": 0.0,
        "EAST WINDSOR-G2": 0.0,
        "GREENFIELD ENERGY CENTRE-G1": 0.0,
        "GREENFIELD ENERGY CENTRE-G2": 0.0,
        "GREENFIELD ENERGY CENTRE-G3": 0.0,
        "GREENFIELD ENERGY CENTRE-G4": 0.0,
        "GREENFIELD SOUTH-G1": 0.0,
        "GREENFIELD SOUTH-G2": 0.0,
        "GTAA-G1": 0.0,
        "GTAA-G2": 0.0,
        "GTAA-G3": 0.0,
        "HALTONHILLS-LT.G1": 0.0,
        "HALTONHILLS-LT.G2": 0.0,
        "HALTONHILLS-LT.G3": 0.0,
        "KAPGS": 0.0,
        "LAKESUPERIOR": 0.0,
        "LENNOX-G1": 0.0,
        "LENNOX-G2": 0.0,
        "LENNOX-G3": 1.0,
        "LENNOX-G4": 1.0,
        "NAPANEE-G1": 0.0,
        "NAPANEE-G2": 0.0,
        "NAPANEE-G3": 0.0,
        "NIPIGONGS": 0.0,
        "NORTHBAYGS": 0.0,
        "NPCOCHRANE": 0.0,
        "NPIROQFALLS": 0.0,
        "NPKIRKLAND-G1-G5": 1.0,
        "NPKIRKLAND-G6": 0.0,
        "PORTLANDS-G1": 0.0,
        "PORTLANDS-G2": 0.0,
        "PORTLANDS-G3": 0.0,
        "SITHE GOREWAY-G11": 0.0,
        "SITHE GOREWAY-G12": 0.0,
        "SITHE GOREWAY-G13": 0.0,
        "SITHE GOREWAY-G15": 0.0,
        "STCLAIRCGS": 0.0,
        "TAOHSC": 0.0,
        "TASARNIA": 122.0,
        "TAWINDSOR": 0.0,
        "THOROLDCGS": 0.0,
        "TUNISGS": 0.0,
        "WESTWINDSOR": 0.0,
        "WHITBYCGS": 0.0,
        "YORKCGS-G1": 0.0,
        "YORKCGS-G2": 0.0,
        "ABKENORA": 7.0,
        "AGUASABON": 31.0,
        "ALEXANDER": 42.0,
        "APIROQUOIS": 58.0,
        "ARNPRIOR": 0.0,
        "AUBREYFALLS": 0.0,
        "BARRETT": 18.0,
        "BECK1": 143.0,
        "BECK2": 896.0,
        "BECK2 PGS": 0.0,
        "CAMERONFALLS": 50.0,
        "CANYON": 0.0,
        "CARIBOUFALLS": 0.0,
        "CARMICHAEL": 17.0,
        "CHATSFALLS": 153.0,
        "CHENAUX": 124.0,
        "CLERGUE": 34.0,
        "DA WATSON": 21.0,
        "DECEWFALLS": 73.0,
        "DECEWND1": 10.0,
        "DESJOACHIMS": 307.0,
        "EARFALLS": 11.0,
        "FORTFRANCSWC": 4.0,
        "GARTSHORE": 0.0,
        "HARMON": 0.0,
        "HARMON 2": 77.0,
        "HARRIS": 5.0,
        "HOLDEN": 235.0,
        "HOLINGSWTH": 0.0,
        "KAKABEKA": 22.0,
        "KIPLING": 0.0,
        "KIPLING 2": 73.0,
        "LITTLELONG": 61.0,
        "LITTLELONG 2": 0.0,
        "LONGSAULTE": 14.0,
        "LOWER WHITE RIVER": 6.0,
        "LOWERNOTCH": 0.0,
        "MACKAYGS": 0.0,
        "MANITOUFALLS": 25.0,
        "MISSION": 6.0,
        "MTNCHUTE": 0.0,
        "NAGAGAMI": 12.0,
        "OTTERRAPIDS": 46.0,
        "PETER SUTHERLAND SR": 24.0,
        "PINEPORTAGE": 19.0,
        "RAYNER": 23.0,
        "REDROCK": 26.0,
        "SAUNDERS": 811.0,
        "SILVERFALLS": 0.0,
        "SMOKY 2": 81.0,
        "STEEPHILL": 2.0,
        "STEWARTVLE": 19.0,
        "UMBATAFALLS": 20.0,
        "UPPER WHITE RIVER": 3.0,
        "WELLS": 0.0,
        "WHITEDOG": 0.0,
        "ADELAIDE": 58.0,
        "AMARANTH": 16.0,
        "AMHERST ISLAND": 70.0,
        "ARMOW": 12.0,
        "BELLE RIVER": 86.0,
        "BLAKE": 59.0,
        "BORNISH": 67.0,
        "BOW LAKE": 15.0,
        "BOW LAKE 2": 32.0,
        "CEDAR POINT 2": 0.0,
        "COMBER": 137.0,
        "CRYSLER": 90.0,
        "DILLON": 73.0,
        "EAST LAKE": 72.0,
        "ERIEAU": 86.0,
        "GOSFIELDWGS": 42.0,
        "GOSHEN": 98.0,
        "GOULAIS": 23.0,
        "GRAND VALLEY 3": 5.0,
        "GRANDWF": 132.0,
        "GREENWICH": 80.0,
        "HENVEY NORTH": 45.0,
        "HENVEY SOUTH": 58.0,
        "JERICHO": 3.0,
        "K2WIND": 122.0,
        "KINGSBRIDGE": 19.0,
        "LANDON": 40.0,
        "MCLEANSMTNWF-LT.AG_T1": 40.0,
        "NORTH KENT": 73.0,
        "PAROCHES": 43.0,
        "PORT BURWELL": 80.0,
        "PORTALMA-T1": 92.0,
        "PORTALMA-T3": 97.0,
        "PRINCEFARM": 144.0,
        "RAILBEDWF-LT.AG_SR": 252.0,
        "RIPLEY SOUTH": 51.0,
        "ROMNEY": 32.0,
        "SANDUSK-LT.AG_T1": 92.0,
        "SHANNON": 5.0,
        "SPENCE": 84.0,
        "SUMMERHAVEN": 84.0,
        "UNDERWOOD": 36.0,
        "WEST LINCOLN NRWF": 164.0,
        "WOLFE ISLAND": 181.0,
        "ZURICH": 98.0,
        "GRANDSF": 0.0,
        "KINGSTONSF": 0.0,
        "NANTICOKE SOLAR": 0.0,
        "NORTHLAND POWER SOLAR FACILITIES": 0.0,
        "SOUTHGATE SF": 0.0,
        "STONE MILLS SF": 0.0,
        "WINDSOR AIRPORT SF": 0.0,
        "ATIKOKAN-G1": 0.0,
        "CALSTOCKGS": 0.0,
        "TBAYBOWATER CTS": 0.0
    }
}