{
    "datetime": "2025-09-14T19:00:00-04:00",
    "production_by_plant": {
        "BRUCEA-G1": 814.0,
        "BRUCEA-G2": 800.0,
        "BRUCEA-G3": 0.0,
        "BRUCEA-G4": 0.0,
        "BRUCEB-G5": 804.0,
        "BRUCEB-G6": 821.0,
        "BRUCEB-G7": 817.0,
        "BRUCEB-G8": 809.0,
        "DARLINGTON-G1": 841.0,
        "DARLINGTON-G2": 855.0,
        "DARLINGTON-G3": 849.0,
        "DARLINGTON-G4": 0.0,
        "PICKERINGA-G1": 0.0,
        "PICKERINGA-G4": 0.0,
        "PICKERINGB-G5": 500.0,
        "PICKERINGB-G6": 508.0,
        "PICKERINGB-G7": 511.0,
        "PICKERINGB-G8": 510.0,
        "BRIGHTON BEACH": 581.0,
        "CARDINAL": 144.0,
        "COCHRANECGS": 0.0,
        "DESTEC": 0.0,
        "DOWCHEMICAL": 0.0,
        "DPNTMTLND": 0.0,
        "EAST WINDSOR-G1": 34.0,
        "EAST WINDSOR-G2": 34.0,
        "GREENFIELD ENERGY CENTRE-G1": 176.0,
        "GREENFIELD ENERGY CENTRE-G2": 176.0,
        "GREENFIELD ENERGY CENTRE-G3": 176.0,
        "GREENFIELD ENERGY CENTRE-G4": 383.0,
        "GREENFIELD SOUTH-G1": 133.0,
        "GREENFIELD SOUTH-G2": 83.0,
        "GTAA-G1": 31.0,
        "GTAA-G2": 0.0,
        "GTAA-G3": 0.0,
        "HALTONHILLS-LT.G1": 204.0,
        "HALTONHILLS-LT.G2": 203.0,
        "HALTONHILLS-LT.G3": 234.0,
        "HYDROGEN READY POWER PLANT (HRPP)": 0.0,
        "KAPGS": 0.0,
        "LAKESUPERIOR": 0.0,
        "LENNOX-G1": 0.0,
        "LENNOX-G2": 0.0,
        "LENNOX-G3": 0.0,
        "LENNOX-G4": 0.0,
        "NAPANEE-G1": 240.0,
        "NAPANEE-G2": 243.0,
        "NAPANEE-G3": 400.0,
        "NIPIGONGS": 0.0,
        "NORTHBAYGS": 0.0,
        "NPIROQFALLS": 0.0,
        "NPKIRKLAND-G1-G5": 76.0,
        "NPKIRKLAND-G6": 0.0,
        "PORTLANDS-G1": 162.0,
        "PORTLANDS-G2": 182.0,
        "PORTLANDS-G3": 194.0,
        "SITHE GOREWAY-G11": 190.0,
        "SITHE GOREWAY-G12": 181.0,
        "SITHE GOREWAY-G13": 184.0,
        "SITHE GOREWAY-G15": 325.0,
        "STCLAIRCGS": 503.0,
        "TAOHSC": 0.0,
        "TASARNIA": 197.0,
        "TAWINDSOR": 0.0,
        "THOROLDCGS": 210.0,
        "TUNISGS": 0.0,
        "WESTWINDSOR": 0.0,
        "WHITBYCGS": 0.0,
        "YORKCGS-G1": 0.0,
        "YORKCGS-G2": 0.0,
        "ABKENORA": 7.0,
        "AGUASABON": 40.0,
        "ALEXANDER": 45.0,
        "APIROQUOIS": 57.0,
        "ARNPRIOR": 0.0,
        "AUBREYFALLS": 0.0,
        "BARRETT": 2.0,
        "BECK1": 163.0,
        "BECK2": 927.0,
        "BECK2 PGS": 5.0,
        "CAMERONFALLS": 57.0,
        "CANYON": 153.0,
        "CARIBOUFALLS": 34.0,
        "CARMICHAEL": 7.0,
        "CHATSFALLS": 49.0,
        "CHENAUX": 35.0,
        "CLERGUE": 34.0,
        "DA WATSON": 67.0,
        "DECEWFALLS": 141.0,
        "DECEWND1": 20.0,
        "DESJOACHIMS": 205.0,
        "EARFALLS": 0.0,
        "FORTFRANCSWC": 9.0,
        "GARTSHORE": 32.0,
        "HARMON": 68.0,
        "HARMON 2": 0.0,
        "HARRIS": 10.0,
        "HOLDEN": 90.0,
        "HOLINGSWTH": 16.0,
        "KAKABEKA": 0.0,
        "KIPLING": 67.0,
        "KIPLING 2": 0.0,
        "LITTLELONG": 0.0,
        "LITTLELONG 2": 63.0,
        "LONGSAULTE": 8.0,
        "LOWER WHITE RIVER": 2.0,
        "LOWERNOTCH": 104.0,
        "MACKAYGS": 0.0,
        "MANITOUFALLS": 0.0,
        "MISSION": 13.0,
        "MTNCHUTE": 69.0,
        "NAGAGAMI": 2.0,
        "OTTERRAPIDS": 48.0,
        "PETER SUTHERLAND SR": 0.0,
        "PINEPORTAGE": 55.0,
        "RAYNER": 0.0,
        "REDROCK": 12.0,
        "SAUNDERS": 743.0,
        "SILVERFALLS": 1.0,
        "SMOKY 2": 79.0,
        "STEEPHILL": 3.0,
        "STEWARTVLE": 0.0,
        "UMBATAFALLS": 4.0,
        "UPPER WHITE RIVER": 2.0,
        "WELLS": 101.0,
        "WHITEDOG": 26.0,
        "ADELAIDE": 12.0,
        "AMARANTH": 5.0,
        "AMHERST ISLAND": 0.0,
        "ARMOW": 18.0,
        "BELLE RIVER": 1.0,
        "BLAKE": 7.0,
        "BORNISH": 14.0,
        "BOW LAKE": 0.0,
        "BOW LAKE 2": 0.0,
        "CEDAR POINT 2": 7.0,
        "COMBER": 1.0,
        "CRYSLER": 21.0,
        "DILLON": 0.0,
        "EAST LAKE": 4.0,
        "ERIEAU": 0.0,
        "GOSFIELDWGS": 0.0,
        "GOSHEN": 17.0,
        "GOULAIS": 1.0,
        "GRAND VALLEY 3": 4.0,
        "GRANDWF": 0.0,
        "GREENWICH": 4.0,
        "HENVEY NORTH": 15.0,
        "HENVEY SOUTH": 22.0,
        "JERICHO": 14.0,
        "K2WIND": 35.0,
        "KINGSBRIDGE": 2.0,
        "LANDON": 9.0,
        "MCLEANSMTNWF-LT.AG_T1": 0.0,
        "NORTH KENT": 1.0,
        "PAROCHES": 0.0,
        "PORT BURWELL": 0.0,
        "PORTALMA-T1": 0.0,
        "PORTALMA-T3": 0.0,
        "PRINCEFARM": 10.0,
        "RAILBEDWF-LT.AG_SR": 0.0,
        "RIPLEY SOUTH": 7.0,
        "ROMNEY": 0.0,
        "SANDUSK-LT.AG_T1": 0.0,
        "SHANNON": 4.0,
        "SPENCE": 0.0,
        "SUMMERHAVEN": 0.0,
        "UNDERWOOD": 7.0,
        "WEST LINCOLN NRWF": 0.0,
        "WOLFE ISLAND": 0.0,
        "ZURICH": 21.0,
        "GRANDSF": 11.0,
        "KINGSTONSF": 8.0,
        "NANTICOKE SOLAR": 5.0,
        "NORTHLAND POWER SOLAR FACILITIES": 6.0,
        "SOUTHGATE SF": 35.0,
        "STONE MILLS SF": 5.0,
        "WINDSOR AIRPORT SF": 7.0,
        "ATIKOKAN-G1": 0.0,
        "CALSTOCKGS": 29.0,
        "TBAYBOWATER CTS": 0.0,
        "GOREWAY BESS": 0.0,
        "ONEIDA ENERGY STORAGE": 143.0,
        "YORK BESS": 2.0
    }
}