{
    "datetime": "2024-06-12T09:00:00-04:00",
    "production_by_plant": {
        "BRUCEA-G1": 812.0,
        "BRUCEA-G2": 704.0,
        "BRUCEA-G3": 0.0,
        "BRUCEA-G4": 792.0,
        "BRUCEB-G5": 818.0,
        "BRUCEB-G6": 0.0,
        "BRUCEB-G7": 1.0,
        "BRUCEB-G8": 817.0,
        "DARLINGTON-G1": 0.0,
        "DARLINGTON-G2": 878.0,
        "DARLINGTON-G3": 826.0,
        "DARLINGTON-G4": 0.0,
        "PICKERINGA-G1": 451.0,
        "PICKERINGA-G4": 504.0,
        "PICKERINGB-G5": 0.0,
        "PICKERINGB-G6": 518.0,
        "PICKERINGB-G7": 461.0,
        "PICKERINGB-G8": 516.0,
        "BRIGHTON BEACH": 271.0,
        "CARDINAL": 0.0,
        "DESTEC": 0.0,
        "DOWCHEMICAL": 8.0,
        "DPNTMTLND": 0.0,
        "EAST WINDSOR-G1": 0.0,
        "EAST WINDSOR-G2": 0.0,
        "GREENFIELD ENERGY CENTRE-G1": 136.0,
        "GREENFIELD ENERGY CENTRE-G2": 136.0,
        "GREENFIELD ENERGY CENTRE-G3": 138.0,
        "GREENFIELD ENERGY CENTRE-G4": 246.0,
        "GREENFIELD SOUTH-G1": 0.0,
        "GREENFIELD SOUTH-G2": 0.0,
        "GTAA-G1": 0.0,
        "GTAA-G2": 0.0,
        "GTAA-G3": 0.0,
        "HALTONHILLS-LT.G1": 0.0,
        "HALTONHILLS-LT.G2": 0.0,
        "HALTONHILLS-LT.G3": 0.0,
        "KAPGS": 0.0,
        "LAKESUPERIOR": 0.0,
        "LENNOX-G1": 0.0,
        "LENNOX-G2": 0.0,
        "LENNOX-G3": 0.0,
        "LENNOX-G4": 0.0,
        "NAPANEE-G1": 0.0,
        "NAPANEE-G2": 0.0,
        "NAPANEE-G3": 0.0,
        "NIPIGONGS": 0.0,
        "NORTHBAYGS": 0.0,
        "NPCOCHRANE": 0.0,
        "NPIROQFALLS": 0.0,
        "NPKIRKLAND-G1-G5": 0.0,
        "NPKIRKLAND-G6": 0.0,
        "PORTLANDS-G1": 166.0,
        "PORTLANDS-G2": 172.0,
        "PORTLANDS-G3": 210.0,
        "SITHE GOREWAY-G11": 159.0,
        "SITHE GOREWAY-G12": 155.0,
        "SITHE GOREWAY-G13": 0.0,
        "SITHE GOREWAY-G15": 162.0,
        "STCLAIRCGS": 0.0,
        "TAOHSC": 0.0,
        "TASARNIA": 259.0,
        "TAWINDSOR": 0.0,
        "THOROLDCGS": 0.0,
        "TUNISGS": 0.0,
        "WESTWINDSOR": 0.0,
        "WHITBYCGS": 0.0,
        "YORKCGS-G1": 0.0,
        "YORKCGS-G2": 0.0,
        "ABKENORA": 12.0,
        "AGUASABON": 37.0,
        "ALEXANDER": 43.0,
        "APIROQUOIS": 0.0,
        "ARNPRIOR": 30.0,
        "AUBREYFALLS": 0.0,
        "BARRETT": 0.0,
        "BECK1": 412.0,
        "BECK2": 1154.0,
        "BECK2 PGS": 1.0,
        "CAMERONFALLS": 56.0,
        "CANYON": 107.0,
        "CARIBOUFALLS": 49.0,
        "CARMICHAEL": 10.0,
        "CHATSFALLS": 94.0,
        "CHENAUX": 68.0,
        "CLERGUE": 31.0,
        "DA WATSON": 20.0,
        "DECEWFALLS": 73.0,
        "DECEWND1": 10.0,
        "DESJOACHIMS": 185.0,
        "EARFALLS": 17.0,
        "FORTFRANCSWC": 4.0,
        "GARTSHORE": 0.0,
        "HARMON": 75.0,
        "HARMON 2": 0.0,
        "HARRIS": 2.0,
        "HOLDEN": 125.0,
        "HOLINGSWTH": 22.0,
        "KAKABEKA": 11.0,
        "KIPLING": 73.0,
        "KIPLING 2": 0.0,
        "LITTLELONG": 61.0,
        "LITTLELONG 2": 0.0,
        "LONGSAULTE": 9.0,
        "LOWER WHITE RIVER": 7.0,
        "LOWERNOTCH": 0.0,
        "MACKAYGS": 5.0,
        "MANITOUFALLS": 53.0,
        "MISSION": 2.0,
        "MTNCHUTE": 65.0,
        "NAGAGAMI": 13.0,
        "OTTERRAPIDS": 44.0,
        "PETER SUTHERLAND SR": 11.0,
        "PINEPORTAGE": 95.0,
        "RAYNER": 27.0,
        "REDROCK": 11.0,
        "SAUNDERS": 730.0,
        "SILVERFALLS": 0.0,
        "SMOKY 2": 82.0,
        "STEEPHILL": 3.0,
        "STEWARTVLE": 18.0,
        "UMBATAFALLS": 17.0,
        "UPPER WHITE RIVER": 4.0,
        "WELLS": 0.0,
        "WHITEDOG": 52.0,
        "ADELAIDE": 11.0,
        "AMARANTH": 12.0,
        "AMHERST ISLAND": 0.0,
        "ARMOW": 65.0,
        "BELLE RIVER": 2.0,
        "BLAKE": 12.0,
        "BORNISH": 19.0,
        "BOW LAKE": 6.0,
        "BOW LAKE 2": 11.0,
        "CEDAR POINT 2": 28.0,
        "COMBER": 1.0,
        "CRYSLER": 2.0,
        "DILLON": 1.0,
        "EAST LAKE": 5.0,
        "ERIEAU": 7.0,
        "GOSFIELDWGS": 0.0,
        "GOSHEN": 18.0,
        "GOULAIS": 6.0,
        "GRAND VALLEY 3": 7.0,
        "GRANDWF": 9.0,
        "GREENWICH": 56.0,
        "HENVEY NORTH": 17.0,
        "HENVEY SOUTH": 31.0,
        "JERICHO": 29.0,
        "K2WIND": 92.0,
        "KINGSBRIDGE": 5.0,
        "LANDON": 13.0,
        "MCLEANSMTNWF-LT.AG_T1": 5.0,
        "NORTH KENT": 6.0,
        "PAROCHES": 0.0,
        "PORT BURWELL": 2.0,
        "PORTALMA-T1": 2.0,
        "PORTALMA-T3": 1.0,
        "PRINCEFARM": 23.0,
        "RAILBEDWF-LT.AG_SR": 14.0,
        "RIPLEY SOUTH": 23.0,
        "ROMNEY": 2.0,
        "SANDUSK-LT.AG_T1": 5.0,
        "SHANNON": 22.0,
        "SPENCE": 5.0,
        "SUMMERHAVEN": 6.0,
        "UNDERWOOD": 60.0,
        "WEST LINCOLN NRWF": 11.0,
        "WOLFE ISLAND": 1.0,
        "ZURICH": 21.0,
        "GRANDSF": 39.0,
        "KINGSTONSF": 13.0,
        "NANTICOKE SOLAR": 18.0,
        "NORTHLAND POWER SOLAR FACILITIES": 13.0,
        "SOUTHGATE SF": 14.0,
        "STONE MILLS SF": 15.0,
        "WINDSOR AIRPORT SF": 14.0,
        "ATIKOKAN-G1": 0.0,
        "CALSTOCKGS": 19.0,
        "TBAYBOWATER CTS": 0.0
    }
}